Workbook

Sheet Factsheet_Fund_Key
A1: as_of | B1: amc | C1: fund_key | D1: asset_class | E1: category | F1: monthly_avg_aum_cr | G1: ter_direct_pct | H1: portfolio_turnover | I1: Fund_Manager | J1: Fund_Manager_experience | K1: Notes
A2: 46022 | B2: Aditya Birla Sun Life Mutual Fund | C2: ABSL_ELSS | D2: =_xlfn.XLOOKUP(C2,mfscreener.portfolio_holdings_v!$C:$C,mfscreener.portfolio_holdings_v!$E:$E) -> ELSS | E2: =_xlfn.XLOOKUP(C2,mfscreener.portfolio_holdings_v!$C:$C,mfscreener.portfolio_holdings_v!$D:$D) -> Equity | F2: 15615.09 | G2: 0.95 | H2: 0.35 | I2: Dhaval Shah | J2: 20
A3: 46022 | B3: Aditya Birla Sun Life Mutual Fund | C3: ABSL_FLEXI_CAP | D3: =_xlfn.XLOOKUP(C3,mfscreener.portfolio_holdings_v!$C:$C,mfscreener.portfolio_holdings_v!$E:$E) -> Flexi Cap | E3: =_xlfn.XLOOKUP(C3,mfscreener.portfolio_holdings_v!$C:$C,mfscreener.portfolio_holdings_v!$D:$D) -> Equity | F3: 24596.21 | G3: 0.32 | H3: 0.86 | I3: Harish Krishnan,Dhaval Joshi | J3: 21,18
A4: 46022 | B4: Aditya Birla Sun Life Mutual Fund | C4: ABSL_FOCUSED | D4: =_xlfn.XLOOKUP(C4,mfscreener.portfolio_holdings_v!$C:$C,mfscreener.portfolio_holdings_v!$E:$E) -> Focused | E4: =_xlfn.XLOOKUP(C4,mfscreener.portfolio_holdings_v!$C:$C,mfscreener.portfolio_holdings_v!$D:$D) -> Equity | F4: 8112.67 | G4: 0.3 | H4: 0.88 | I4: Kunal Sangoi | J4: 20
A5: 46022 | B5: Aditya Birla Sun Life Mutual Fund | C5: ABSL_LARGE_CAP | D5: =_xlfn.XLOOKUP(C5,mfscreener.portfolio_holdings_v!$C:$C,mfscreener.portfolio_holdings_v!$E:$E) -> Large Cap | E5: =_xlfn.XLOOKUP(C5,mfscreener.portfolio_holdings_v!$C:$C,mfscreener.portfolio_holdings_v!$D:$D) -> Equity | F5: 31160.13 | G5: 0.55 | H5: 0.97 | I5: Mahesh Patil | J5: 31
A6: 46022 | B6: Aditya Birla Sun Life Mutual Fund | C6: ABSL_LARGE_MID_CAP | D6: =_xlfn.XLOOKUP(C6,mfscreener.portfolio_holdings_v!$C:$C,mfscreener.portfolio_holdings_v!$E:$E) -> Large & Mid Cap | E6: =_xlfn.XLOOKUP(C6,mfscreener.portfolio_holdings_v!$C:$C,mfscreener.portfolio_holdings_v!$D:$D) -> Equity | F6: 5842.88 | G6: 0.59 | H6: 1.08 | I6: Vishal Gajwani | J6: 19
A7: 46022 | B7: Aditya Birla Sun Life Mutual Fund | C7: ABSL_MID_CAP | D7: =_xlfn.XLOOKUP(C7,mfscreener.portfolio_holdings_v!$C:$C,mfscreener.portfolio_holdings_v!$E:$E) -> Mid Cap | E7: =_xlfn.XLOOKUP(C7,mfscreener.portfolio_holdings_v!$C:$C,mfscreener.portfolio_holdings_v!$D:$D) -> Equity | F7: 6267.84 | G7: 0.85 | H7: 1.02 | I7: Mr. Chanchal Khandelwal | J7: 15
A8: 46022 | B8: Aditya Birla Sun Life Mutual Fund | C8: ABSL_MULTI_CAP | D8: =_xlfn.XLOOKUP(C8,mfscreener.portfolio_holdings_v!$C:$C,mfscreener.portfolio_holdings_v!$E:$E) -> Multi Cap | E8: =_xlfn.XLOOKUP(C8,mfscreener.portfolio_holdings_v!$C:$C,mfscreener.portfolio_holdings_v!$D:$D) -> Equity | F8: 6752.33 | G8: 0.63 | H8: 0.75 | I8: Abhinav Khandelwal,Harshil Suvarnkar | J8: 15,15
A9: 46022 | B9: Aditya Birla Sun Life Mutual Fund | C9: ABSL_SMALL_CAP | D9: =_xlfn.XLOOKUP(C9,mfscreener.portfolio_holdings_v!$C:$C,mfscreener.portfolio_holdings_v!$E:$E) -> Small Cap | E9: =_xlfn.XLOOKUP(C9,mfscreener.portfolio_holdings_v!$C:$C,mfscreener.portfolio_holdings_v!$D:$D) -> Equity | F9: 5097.16 | G9: 0.51 | H9: 0.9 | I9: Abhinav Khandelwal,Dhaval Joshi | J9: 15,18
A10: 46022 | B10: Aditya Birla Sun Life Mutual Fund | C10: ABSL_VALUE | D10: =_xlfn.XLOOKUP(C10,mfscreener.portfolio_holdings_v!$C:$C,mfscreener.portfolio_holdings_v!$E:$E) -> Value | E10: =_xlfn.XLOOKUP(C10,mfscreener.portfolio_holdings_v!$C:$C,mfscreener.portfolio_holdings_v!$D:$D) -> Equity | F10: 6338.33 | G10: 0.72 | H10: 1.02 | I10: Kunal Sangoi | J10: 20
A11: 46022 | B11: Aditya Birla Sun Life Mutual Fund | C11: ABSL_BANKING_FINANCIAL | D11: =_xlfn.XLOOKUP(C11,mfscreener.portfolio_holdings_v!$C:$C,mfscreener.portfolio_holdings_v!$E:$E) -> Banking & Financial Services | E11: =_xlfn.XLOOKUP(C11,mfscreener.portfolio_holdings_v!$C:$C,mfscreener.portfolio_holdings_v!$D:$D) -> Equity | F11: 3660.74 | G11: 0.99 | H11: 0.34 | I11: Dhaval Gala | J11: 19
A12: 46022 | B12: Aditya Birla Sun Life Mutual Fund | C12: ABSL_MANUFACTURING | D12: Manufacturing | E12: =_xlfn.XLOOKUP(C12,mfscreener.portfolio_holdings_v!$C:$C,mfscreener.portfolio_holdings_v!$D:$D) -> Equity | F12: 1107.08 | G12: 1.34 | H12: 0.31 | I12: Harish Krishnan | J12: 15
A13: 46022 | B13: Aditya Birla Sun Life Mutual Fund | C13: ABSL_PSU_EQUITY | D13: =_xlfn.XLOOKUP(C13,mfscreener.portfolio_holdings_v!$C:$C,mfscreener.portfolio_holdings_v!$E:$E) -> PSU Equity | E13: =_xlfn.XLOOKUP(C13,mfscreener.portfolio_holdings_v!$C:$C,mfscreener.portfolio_holdings_v!$D:$D) -> Equity | F13: 5680.9 | G13: 0.61 | H13: 0.24 | I13: Dhaval Gala | J13: 19
A14: 46022 | B14: Aditya Birla Sun Life Mutual Fund | C14: ABSL_PHARMA_HEALTHCARE | D14: Healthcare | E14: =_xlfn.XLOOKUP(C14,mfscreener.portfolio_holdings_v!$C:$C,mfscreener.portfolio_holdings_v!$D:$D) -> Equity | F14: 850.88 | G14: 1.02 | H14: 0.31 | I14: Mr. Dhaval Shah | J14: 20
A15: 46022 | B15: Aditya Birla Sun Life Mutual Fund | C15: ABSL_DIGITAL_INDIA | D15: Technology | E15: =_xlfn.XLOOKUP(C15,mfscreener.portfolio_holdings_v!$C:$C,mfscreener.portfolio_holdings_v!$D:$D) -> Equity | F15: 4788.07 | G15: 0.79 | H15: 0.48 | I15: Kunal Sangoi | J15: 20
A16: 46022 | B16: Aditya Birla Sun Life Mutual Fund | C16: ABSL_CONGLOMERATE | D16: =_xlfn.XLOOKUP(C16,mfscreener.portfolio_holdings_v!$C:$C,mfscreener.portfolio_holdings_v!$E:$E) -> Conglomerate | E16: =_xlfn.XLOOKUP(C16,mfscreener.portfolio_holdings_v!$C:$C,mfscreener.portfolio_holdings_v!$D:$D) -> Equity | F16: 1763.06 | G16: 0.7 | I16: Harish Krishnan , Kunal Sangoi | J16: 15,20
A17: 46022 | B17: Aditya Birla Sun Life Mutual Fund | C17: ABSL_BUSINESS_CYCLE | D17: =_xlfn.XLOOKUP(C17,mfscreener.portfolio_holdings_v!$C:$C,mfscreener.portfolio_holdings_v!$E:$E) -> Business Cycle | E17: =_xlfn.XLOOKUP(C17,mfscreener.portfolio_holdings_v!$C:$C,mfscreener.portfolio_holdings_v!$D:$D) -> Equity | F17: 1796.68 | G17: 1.15 | H17: 0.36 | I17: Harish Krishnan, dhaval gala | J17: 15 , 19
A18: 46022 | B18: Aditya Birla Sun Life Mutual Fund | C18: ABSL_INFRASTRUCTURE | D18: =_xlfn.XLOOKUP(C18,mfscreener.portfolio_holdings_v!$C:$C,mfscreener.portfolio_holdings_v!$E:$E) -> Infrastructure | E18: =_xlfn.XLOOKUP(C18,mfscreener.portfolio_holdings_v!$C:$C,mfscreener.portfolio_holdings_v!$D:$D) -> Equity | F18: 1145.24 | G18: 1.42 | H18: 0.44 | I18: Mr. Mahesh Patil ,Mr. Jonas Bhutta | J18: 31
A19: 46022 | B19: Aditya Birla Sun Life Mutual Fund | C19: ABSL_TRANSPORT_LOGISTICS | D19: =_xlfn.XLOOKUP(C19,mfscreener.portfolio_holdings_v!$C:$C,mfscreener.portfolio_holdings_v!$E:$E) -> Transportation & Logistics | E19: =_xlfn.XLOOKUP(C19,mfscreener.portfolio_holdings_v!$C:$C,mfscreener.portfolio_holdings_v!$D:$D) -> Equity | F19: 1595.14 | G19: 0.78 | H19: 0.14 | I19: Dhaval Gala | J19: 19
A20: 46022 | B20: Aditya Birla Sun Life Mutual Fund | C20: ABSL_MNC | D20: =_xlfn.XLOOKUP(C20,mfscreener.portfolio_holdings_v!$C:$C,mfscreener.portfolio_holdings_v!$E:$E) -> MNC | E20: =_xlfn.XLOOKUP(C20,mfscreener.portfolio_holdings_v!$C:$C,mfscreener.portfolio_holdings_v!$D:$D) -> Equity | F20: 3659.55 | G20: 1.3 | H20: 0.2 | I20: Chanchal Khandelwal | J20: 15
A21: 46022 | B21: Aditya Birla Sun Life Mutual Fund | C21: ABSL_QUANT | D21: =_xlfn.XLOOKUP(C21,mfscreener.portfolio_holdings_v!$C:$C,mfscreener.portfolio_holdings_v!$E:$E) -> Quant | E21: =_xlfn.XLOOKUP(C21,mfscreener.portfolio_holdings_v!$C:$C,mfscreener.portfolio_holdings_v!$D:$D) -> Equity | F21: 2362.84 | G21: 0.65 | I21: Harish Krishnan | J21: 15
A22: 46022 | B22: Aditya Birla Sun Life Mutual Fund | C22: ABSL_BALANCED_ADVANTAGE | D22: =_xlfn.XLOOKUP(C22,mfscreener.portfolio_holdings_v!$C:$C,mfscreener.portfolio_holdings_v!$E:$E) -> Balanced Advantage | E22: =_xlfn.XLOOKUP(C22,mfscreener.portfolio_holdings_v!$C:$C,mfscreener.portfolio_holdings_v!$D:$D) -> Hybrid | F22: 8688.64 | G22: 0.67 | H22: 2.44 | I22: Mohit Sharma, Mr. Lovelish Solanki ,Mr. Harish Krishnan | J22: ,10 , 21
A23: 46022 | B23: Aditya Birla Sun Life Mutual Fund | C23: ABSL_MULTI_ASSET | D23: =_xlfn.XLOOKUP(C23,mfscreener.portfolio_holdings_v!$C:$C,mfscreener.portfolio_holdings_v!$E:$E) -> Multi Asset Allocation | E23: =_xlfn.XLOOKUP(C23,mfscreener.portfolio_holdings_v!$C:$C,mfscreener.portfolio_holdings_v!$D:$D) -> Hybrid | F23: 5068.21 | G23: 0.59 | H23: 0.57 | I23: Mr. Dhaval Gala, Mr. Bhupesh Bameta ,Mr. Sachin Wankhede | J23: 19, 17, 23
A24: 46022 | B24: Aditya Birla Sun Life Mutual Fund | C24: ABSL_EQUITY_HYBRID_95 | D24: =_xlfn.XLOOKUP(C24,mfscreener.portfolio_holdings_v!$C:$C,mfscreener.portfolio_holdings_v!$E:$E) -> Equity Hybrid 95 | E24: =_xlfn.XLOOKUP(C24,mfscreener.portfolio_holdings_v!$C:$C,mfscreener.portfolio_holdings_v!$D:$D) -> Hybrid | F24: 7563.45 | G24: 1.09 | H24: 0.55 | I24: mr. Harshil Suvarnkar ,Mr. Chanchal Khandelwal | J24: 15,15
A25: 46022 | B25: Aditya Birla Sun Life Mutual Fund | C25: ABSL_EQUITY_SAVINGS | D25: =_xlfn.XLOOKUP(C25,mfscreener.portfolio_holdings_v!$C:$C,mfscreener.portfolio_holdings_v!$E:$E) -> Equity Savings | E25: =_xlfn.XLOOKUP(C25,mfscreener.portfolio_holdings_v!$C:$C,mfscreener.portfolio_holdings_v!$D:$D) -> Hybrid | F25: 943.21 | G25: 0.53 | H25: 6.83 | I25: Atul Penkar, Mr. Harshil Suvarnkar & Mr. Lovelish Solanki | J25: 25, 15 , 10
A26: 46022 | B26: Aditya Birla Sun Life Mutual Fund | C26: ABSL_REGULAR_SAVINGS | D26: =_xlfn.XLOOKUP(C26,mfscreener.portfolio_holdings_v!$C:$C,mfscreener.portfolio_holdings_v!$E:$E) -> Regular Savings | E26: =_xlfn.XLOOKUP(C26,mfscreener.portfolio_holdings_v!$C:$C,mfscreener.portfolio_holdings_v!$D:$D) -> Hybrid | F26: 1552.73 | G26: 0.93 | H26: 1.18
A27: 46022 | B27: 360 ONE Mutual Fund | C27: ONE360_BALANCED_HYBRID | D27: =_xlfn.XLOOKUP(C27,mfscreener.portfolio_holdings_v!$C:$C,mfscreener.portfolio_holdings_v!$E:$E) -> Balanced Hybrid | E27: =_xlfn.XLOOKUP(C27,mfscreener.portfolio_holdings_v!$C:$C,mfscreener.portfolio_holdings_v!$D:$D) -> Hybrid | F27: 841.6 | G27: 0.45 | H27: 0.55 | I27: Mr. Mayur Patel, Mr. Milan Mody | J27: 20,20
A28: 46022 | B28: 360 ONE Mutual Fund | C28: ONE360_FLEXI_CAP | D28: =_xlfn.XLOOKUP(C28,mfscreener.portfolio_holdings_v!$C:$C,mfscreener.portfolio_holdings_v!$E:$E) -> Flexi Cap | E28: =_xlfn.XLOOKUP(C28,mfscreener.portfolio_holdings_v!$C:$C,mfscreener.portfolio_holdings_v!$D:$D) -> Equity | F28: 2087.06 | G28: 0.48 | H28: 0.43 | I28: Mr. Mayur Patel | J28: 20
A29: 46022 | B29: 360 ONE Mutual Fund | C29: ONE360_FOCUSED | D29: =_xlfn.XLOOKUP(C29,mfscreener.portfolio_holdings_v!$C:$C,mfscreener.portfolio_holdings_v!$E:$E) -> Focused | E29: =_xlfn.XLOOKUP(C29,mfscreener.portfolio_holdings_v!$C:$C,mfscreener.portfolio_holdings_v!$D:$D) -> Equity | F29: 7229.59 | G29: 0.81 | H29: 0.42 | I29: Mr. Mayur Patel | J29: 20
A30: 46022 | B30: 360 ONE Mutual Fund | C30: ONE360_QUANT | D30: =_xlfn.XLOOKUP(C30,mfscreener.portfolio_holdings_v!$C:$C,mfscreener.portfolio_holdings_v!$E:$E) -> Quant | E30: =_xlfn.XLOOKUP(C30,mfscreener.portfolio_holdings_v!$C:$C,mfscreener.portfolio_holdings_v!$D:$D) -> Equity | F30: 893.6 | G30: 0.62 | H30: 1.1 | I30: Mr. Ashish Ongari | J30: 6
A31: 46022 | B31: Axis Mutual Fund | C31: AXIS_ELSS | D31: =_xlfn.XLOOKUP(C31,mfscreener.portfolio_holdings_v!$C:$C,mfscreener.portfolio_holdings_v!$E:$E) -> ELSS | E31: =_xlfn.XLOOKUP(C31,mfscreener.portfolio_holdings_v!$C:$C,mfscreener.portfolio_holdings_v!$D:$D) -> Equity | F31: 34449.51 | G31: 0.81 | H31: 0.25 | I31: Mr. Shreyash Devalkar, Mr. Ashish Naik | J31: 21,17
A32: 46022 | B32: Axis Mutual Fund | C32: AXIS_FLEXI_CAP | D32: =_xlfn.XLOOKUP(C32,mfscreener.portfolio_holdings_v!$C:$C,mfscreener.portfolio_holdings_v!$E:$E) -> Flexi Cap | E32: =_xlfn.XLOOKUP(C32,mfscreener.portfolio_holdings_v!$C:$C,mfscreener.portfolio_holdings_v!$D:$D) -> Equity | F32: 13090.34 | G32: 0.72 | H32: 0.18 | I32: Mr. Sachin Relekar, Ms. Krishnaa N | J32: 24,5
A33: 46022 | B33: Axis Mutual Fund | C33: AXIS_FOCUSED | D33: =_xlfn.XLOOKUP(C33,mfscreener.portfolio_holdings_v!$C:$C,mfscreener.portfolio_holdings_v!$E:$E) -> Focused | E33: =_xlfn.XLOOKUP(C33,mfscreener.portfolio_holdings_v!$C:$C,mfscreener.portfolio_holdings_v!$D:$D) -> Equity | F33: 12149.35 | G33: 0.84 | H33: 0.21 | I33: Mr. Sachin Relekar, Ms. Krishnaa N | J33: 24,5
A34: 46022 | B34: Axis Mutual Fund | C34: AXIS_LARGE_CAP | D34: =_xlfn.XLOOKUP(C34,mfscreener.portfolio_holdings_v!$C:$C,mfscreener.portfolio_holdings_v!$E:$E) -> Large Cap | E34: =_xlfn.XLOOKUP(C34,mfscreener.portfolio_holdings_v!$C:$C,mfscreener.portfolio_holdings_v!$D:$D) -> Equity | F34: 33618.06 | G34: 0.72 | H34: 0.86 | I34: Mr. Shreyash Devalkar, Mr. Jayesh Sundar ,Ms. Krishnaa N | J34: 21,22,5
A35: 46022 | B35: Axis Mutual Fund | C35: AXIS_LARGE_MID_CAP | D35: =_xlfn.XLOOKUP(C35,mfscreener.portfolio_holdings_v!$C:$C,mfscreener.portfolio_holdings_v!$E:$E) -> Large & Mid Cap | E35: =_xlfn.XLOOKUP(C35,mfscreener.portfolio_holdings_v!$C:$C,mfscreener.portfolio_holdings_v!$D:$D) -> Equity | F35: 15508.91 | G35: 0.59 | H35: 0.61 | I35: Mr. Shreyash Devalkar ,Mr. Hitesh Das, Ms. Krishnaa N | J35: 21,14,5
A36: 46022 | B36: Axis Mutual Fund | C36: AXIS_MID_CAP | D36: =_xlfn.XLOOKUP(C36,mfscreener.portfolio_holdings_v!$C:$C,mfscreener.portfolio_holdings_v!$E:$E) -> Mid Cap | E36: =_xlfn.XLOOKUP(C36,mfscreener.portfolio_holdings_v!$C:$C,mfscreener.portfolio_holdings_v!$D:$D) -> Equity | F36: 31710.81 | G36: 0.55 | H36: 0.43 | I36: Mr. Shreyash Devalkar ,Mr. Hitesh Das, Ms. Krishnaa N | J36: 21,14,5
A37: 46022 | B37: Axis Mutual Fund | C37: AXIS_MULTI_CAP | D37: =_xlfn.XLOOKUP(C37,mfscreener.portfolio_holdings_v!$C:$C,mfscreener.portfolio_holdings_v!$E:$E) -> Multi Cap | E37: =_xlfn.XLOOKUP(C37,mfscreener.portfolio_holdings_v!$C:$C,mfscreener.portfolio_holdings_v!$D:$D) -> Equity | F37: 9185.27 | G37: 0.72 | H37: 0.45 | I37: Mr. Nitin Arora ,Mr. Shreyash Devalkar, Mr. Hitesh Das | J37: 14,21,14
A38: 46022 | B38: Axis Mutual Fund | C38: AXIS_SMALL_CAP | D38: =_xlfn.XLOOKUP(C38,mfscreener.portfolio_holdings_v!$C:$C,mfscreener.portfolio_holdings_v!$E:$E) -> Small Cap | E38: =_xlfn.XLOOKUP(C38,mfscreener.portfolio_holdings_v!$C:$C,mfscreener.portfolio_holdings_v!$D:$D) -> Equity | F38: 26486.45 | G38: 0.57 | H38: 0.34 | I38: Mr. Tejas Sheth, Mr. Mayank Hyanki , Ms. Krishnaa N | J38: 21,15 ,5
A39: 46022 | B39: Axis Mutual Fund | C39: AXIS_VALUE | D39: =_xlfn.XLOOKUP(C39,mfscreener.portfolio_holdings_v!$C:$C,mfscreener.portfolio_holdings_v!$E:$E) -> Value | E39: =_xlfn.XLOOKUP(C39,mfscreener.portfolio_holdings_v!$C:$C,mfscreener.portfolio_holdings_v!$D:$D) -> Equity | F39: 1299.23 | G39: 0.73 | H39: 0.41 | I39: Mr. Nitin Arora, Ms. Krishnaa N | J39: 24,5
A40: 46022 | B40: Axis Mutual Fund | C40: AXIS_INNOVATION | D40: =_xlfn.XLOOKUP(C40,mfscreener.portfolio_holdings_v!$C:$C,mfscreener.portfolio_holdings_v!$E:$E) -> Thematic | E40: =_xlfn.XLOOKUP(C40,mfscreener.portfolio_holdings_v!$C:$C,mfscreener.portfolio_holdings_v!$D:$D) -> Equity | F40: 1195.08 | G40: 1.29 | H40: 0.71 | I40: Mr. Ashish Naik , Ms. Krishnaa N | J40: 17 , 5
A41: 46022 | B41: Axis Mutual Fund | C41: AXIS_ESG | D41: =_xlfn.XLOOKUP(C41,mfscreener.portfolio_holdings_v!$C:$C,mfscreener.portfolio_holdings_v!$E:$E) -> ESG | E41: =_xlfn.XLOOKUP(C41,mfscreener.portfolio_holdings_v!$C:$C,mfscreener.portfolio_holdings_v!$D:$D) -> Equity | F41: 1206.73 | G41: 1.34 | H41: 0.3 | I41: Vishal Agarwa , Krishna S | J41: 15 , 5
A42: 46022 | B42: Axis Mutual Fund | C42: AXIS_QUANT | D42: =_xlfn.XLOOKUP(C42,mfscreener.portfolio_holdings_v!$C:$C,mfscreener.portfolio_holdings_v!$E:$E) -> Quant | E42: =_xlfn.XLOOKUP(C42,mfscreener.portfolio_holdings_v!$C:$C,mfscreener.portfolio_holdings_v!$D:$D) -> Equity | F42: 911.53 | G42: 0.74 | H42: 1.52 | I42: Mr. Karthik Kumar , Krishna S | J42: 16,5
A43: 46022 | B43: Axis Mutual Fund | C43: AXIS_BUSINESS_CYCLE | D43: =_xlfn.XLOOKUP(C43,mfscreener.portfolio_holdings_v!$C:$C,mfscreener.portfolio_holdings_v!$E:$E) -> Business Cycle | E43: =_xlfn.XLOOKUP(C43,mfscreener.portfolio_holdings_v!$C:$C,mfscreener.portfolio_holdings_v!$D:$D) -> Equity | F43: 2212.52 | G43: 0.87 | H43: 0.68 | I43: Mr. Ashish Naik | J43: 17
A44: 46022 | B44: Axis Mutual Fund | C44: AXIS_MANUFACTURING | D44: =_xlfn.XLOOKUP(C44,mfscreener.portfolio_holdings_v!$C:$C,mfscreener.portfolio_holdings_v!$E:$E) -> Manufacturing | E44: =_xlfn.XLOOKUP(C44,mfscreener.portfolio_holdings_v!$C:$C,mfscreener.portfolio_holdings_v!$D:$D) -> Equity | F44: 5118.62 | G44: 0.54 | H44: 0.57 | I44: Mr. Nitin Arora | J44: 14
A45: 46022 | B45: Axis Mutual Fund | C45: AXIS_CONSUMPTION | D45: =_xlfn.XLOOKUP(C45,mfscreener.portfolio_holdings_v!$C:$C,mfscreener.portfolio_holdings_v!$E:$E) -> Consumption | E45: =_xlfn.XLOOKUP(C45,mfscreener.portfolio_holdings_v!$C:$C,mfscreener.portfolio_holdings_v!$D:$D) -> Equity | F45: 3543.85 | G45: 0.6 | H45: 0.47 | I45: Mr. Hitesh Das | J45: 14
A46: 46022 | B46: Axis Mutual Fund | C46: AXIS_MOMENTUM | D46: =_xlfn.XLOOKUP(C46,mfscreener.portfolio_holdings_v!$C:$C,mfscreener.portfolio_holdings_v!$E:$E) -> Momentum | E46: =_xlfn.XLOOKUP(C46,mfscreener.portfolio_holdings_v!$C:$C,mfscreener.portfolio_holdings_v!$D:$D) -> Equity | F46: 1210.72 | G46: 0.61 | H46: 1.6 | I46: Mr. Karthik Kumar | J46: 16
A47: 46022 | B47: Axis Mutual Fund | C47: AXIS_SERVICES_OPPORTUNITIES | D47: =_xlfn.XLOOKUP(C47,mfscreener.portfolio_holdings_v!$C:$C,mfscreener.portfolio_holdings_v!$E:$E) -> Services Opportunities | E47: =_xlfn.XLOOKUP(C47,mfscreener.portfolio_holdings_v!$C:$C,mfscreener.portfolio_holdings_v!$D:$D) -> Equity | F47: 1901.5 | G47: 0.7 | I47: Mr. Sachin Relekar, Ms. Krishnaa N | J47: 24,5
A48: 46022 | B48: Axis Mutual Fund | C48: AXIS_CONSERVATIVE_HYBRID | D48: =_xlfn.XLOOKUP(C48,mfscreener.portfolio_holdings_v!$C:$C,mfscreener.portfolio_holdings_v!$E:$E) -> Conservative Hybrid | E48: =_xlfn.XLOOKUP(C48,mfscreener.portfolio_holdings_v!$C:$C,mfscreener.portfolio_holdings_v!$D:$D) -> Hybrid | F48: 234.6 | G48: 1.11 | I48: Mr. Devang Shah ,Mr. Sachin Jain ,Mr. Jayesh Sundar | J48: 20,12,22
A49: 46022 | B49: Axis Mutual Fund | C49: AXIS_EQUITY_SAVINGS | D49: =_xlfn.XLOOKUP(C49,mfscreener.portfolio_holdings_v!$C:$C,mfscreener.portfolio_holdings_v!$E:$E) -> Equity Savings | E49: =_xlfn.XLOOKUP(C49,mfscreener.portfolio_holdings_v!$C:$C,mfscreener.portfolio_holdings_v!$D:$D) -> Hybrid | F49: 928.1 | G49: 1.06 | I49: Mr. Mayank Hyanki, Mr. Devang Shah, Mr. Hardik Shah ,Ms. Krishnaa N | J49: 15,20,16,5
A50: 46022 | B50: Axis Mutual Fund | C50: AXIS_MULTI_ASSET | D50: =_xlfn.XLOOKUP(C50,mfscreener.portfolio_holdings_v!$C:$C,mfscreener.portfolio_holdings_v!$E:$E) -> Multi Asset Allocation | E50: =_xlfn.XLOOKUP(C50,mfscreener.portfolio_holdings_v!$C:$C,mfscreener.portfolio_holdings_v!$D:$D) -> Hybrid | F50: 1831.79 | G50: 0.92 | I50: Mr. Ashish Naik ,Mr. Devang Shah, Mr. Hardik Shah ,Mr. Aditya Pagaria, Mr. Pratik Tibrewal ,Ms. Krishn | J50: 17,20,16,17,14,5
A51: 46022 | B51: Axis Mutual Fund | C51: AXIS_AGGRESSIVE_HYBRID | D51: =_xlfn.XLOOKUP(C51,mfscreener.portfolio_holdings_v!$C:$C,mfscreener.portfolio_holdings_v!$E:$E) -> Aggressive Hybrid | E51: =_xlfn.XLOOKUP(C51,mfscreener.portfolio_holdings_v!$C:$C,mfscreener.portfolio_holdings_v!$D:$D) -> Hybrid | F51: 1551.98 | G51: 1.08 | I51: Mr. Jayesh Sundar, Mr. Devang Shah, Mr. Aditya Pagaria, Ms. Krishnaa N | J51: 22,20,17,5
A52: 46022 | B52: Axis Mutual Fund | C52: AXIS_CHILDRENS | D52: =_xlfn.XLOOKUP(C52,mfscreener.portfolio_holdings_v!$C:$C,mfscreener.portfolio_holdings_v!$E:$E) -> Children's Fund | E52: =_xlfn.XLOOKUP(C52,mfscreener.portfolio_holdings_v!$C:$C,mfscreener.portfolio_holdings_v!$D:$D) -> Hybrid | F52: 920.63 | G52: 1.38 | I52: Mr. Jayesh Sundar, Mr. Devang Shah ,Mr. Hardik Shah ,Ms. Krishnaa N | J52: 22,20,16,6
A53: 46022 | B53: Axis Mutual Fund | C53: AXIS_BALANCED_ADVANTAGE | D53: =_xlfn.XLOOKUP(C53,mfscreener.portfolio_holdings_v!$C:$C,mfscreener.portfolio_holdings_v!$E:$E) -> Balanced Advantage | E53: =_xlfn.XLOOKUP(C53,mfscreener.portfolio_holdings_v!$C:$C,mfscreener.portfolio_holdings_v!$D:$D) -> Hybrid | F53: 3801.02 | G53: 0.73 | I53: Mr. Jayesh Sundar ,Mr. Devang Shah, Mr. Hardik Shah | J53: 22,20,16
A54: 46022 | B54: Axis Mutual Fund | C54: AXIS_ARBITRAGE | D54: =_xlfn.XLOOKUP(C54,mfscreener.portfolio_holdings_v!$C:$C,mfscreener.portfolio_holdings_v!$E:$E) -> Arbitrage | E54: =_xlfn.XLOOKUP(C54,mfscreener.portfolio_holdings_v!$C:$C,mfscreener.portfolio_holdings_v!$D:$D) -> Hybrid | F54: 8103.39 | G54: 0.33 | I54: Mr. Karthik Kumar, Mr. Devang Shah, Mr. Sachin Jain | J54: 16,20,12
A55: 46022 | B55: Bajaj Finserv Mutual Fund | C55: BAJAJ_FLEXI_CAP | D55: =_xlfn.XLOOKUP(C55,mfscreener.portfolio_holdings_v!$C:$C,mfscreener.portfolio_holdings_v!$E:$E) -> Flexi Cap | E55: =_xlfn.XLOOKUP(C55,mfscreener.portfolio_holdings_v!$C:$C,mfscreener.portfolio_holdings_v!$D:$D) -> Equity | F55: 6158.13 | G55: 0.48 | H55: 0.93 | I55: Mr. Nimesh Chandan, Mr. Sorbh Gupta ,Mr. Siddharth Chaudhary | J55: 25,16,18
A56: 46022 | B56: Bajaj Finserv Mutual Fund | C56: BAJAJ_LARGE_CAP | D56: =_xlfn.XLOOKUP(C56,mfscreener.portfolio_holdings_v!$C:$C,mfscreener.portfolio_holdings_v!$E:$E) -> Large Cap | E56: =_xlfn.XLOOKUP(C56,mfscreener.portfolio_holdings_v!$C:$C,mfscreener.portfolio_holdings_v!$D:$D) -> Equity | F56: 1661.13 | G56: 0.59 | H56: 1.11 | I56: Mr. Nimesh Chandan, Mr. Sorbh Gupta ,Mr. Siddharth Chaudhary | J56: 25,16,18
A57: 46022 | B57: Bajaj Finserv Mutual Fund | C57: BAJAJ_LARGE_MID_CAP | D57: =_xlfn.XLOOKUP(C57,mfscreener.portfolio_holdings_v!$C:$C,mfscreener.portfolio_holdings_v!$E:$E) -> Large & Mid Cap | E57: =_xlfn.XLOOKUP(C57,mfscreener.portfolio_holdings_v!$C:$C,mfscreener.portfolio_holdings_v!$D:$D) -> Equity | F57: 2280.92 | G57: 0.59 | H57: 1.15 | I57: Mr. Nimesh Chandan, Mr. Sorbh Gupta ,Mr. Siddharth Chaudhary | J57: 25,16,18
A58: 46022 | B58: Bajaj Finserv Mutual Fund | C58: BAJAJ_SMALL_CAP | D58: =_xlfn.XLOOKUP(C58,mfscreener.portfolio_holdings_v!$C:$C,mfscreener.portfolio_holdings_v!$E:$E) -> Small Cap | E58: =_xlfn.XLOOKUP(C58,mfscreener.portfolio_holdings_v!$C:$C,mfscreener.portfolio_holdings_v!$D:$D) -> Equity | F58: 1519.23 | G58: 0.44 | I58: Mr. Nimesh Chandan, Mr. Sorbh Gupta ,Mr. Siddharth Chaudhary | J58: 25,16,18
A59: 46022 | B59: Bajaj Finserv Mutual Fund | C59: BAJAJ_CONSUMPTION | D59: Consumption | E59: =_xlfn.XLOOKUP(C59,mfscreener.portfolio_holdings_v!$C:$C,mfscreener.portfolio_holdings_v!$D:$D) -> Equity | F59: 676.06 | G59: 0.72 | I59: Mr. Sorbh Gupta (Equity Portion), Mr. Sayan Das Sharma (Equity Portion), Mr. Siddharth Chaudhary (Debt Portion) | J59: 16, 11,18
A60: 46022 | B60: Bajaj Finserv Mutual Fund | C60: BAJAJ_ELSS | D60: =_xlfn.XLOOKUP(C60,mfscreener.portfolio_holdings_v!$C:$C,mfscreener.portfolio_holdings_v!$E:$E) -> ELSS | E60: =_xlfn.XLOOKUP(C60,mfscreener.portfolio_holdings_v!$C:$C,mfscreener.portfolio_holdings_v!$D:$D) -> Equity | F60: 72.43 | G60: 0.49 | I60: Mr. Nimesh Chandan, Mr. Sorbh Gupta ,Mr. Siddharth Chaudhary | J60: 25,16,18
A61: 46022 | B61: Bajaj Finserv Mutual Fund | C61: BAJAJ_BANKING_FINANCIAL_SERVICES | D61: Banking & Financial Services | E61: =_xlfn.XLOOKUP(C61,mfscreener.portfolio_holdings_v!$C:$C,mfscreener.portfolio_holdings_v!$D:$D) -> Equity
A62: 46022 | B62: Bajaj Finserv Mutual Fund | C62: BAJAJ_HEALTHCARE | D62: Healthcare | E62: =_xlfn.XLOOKUP(C62,mfscreener.portfolio_holdings_v!$C:$C,mfscreener.portfolio_holdings_v!$D:$D) -> Equity | F62: 337.56 | G62: 0.72 | I62: Mr. Nimesh Chandan, Mr. Sorbh Gupta ,Mr. Siddharth Chaudhary | J62: 25,16,18
A63: 46022 | B63: Bajaj Finserv Mutual Fund | C63: BAJAJ_MULTI_ASSET | D63: =_xlfn.XLOOKUP(C63,mfscreener.portfolio_holdings_v!$C:$C,mfscreener.portfolio_holdings_v!$E:$E) -> Multi Asset Allocation | E63: =_xlfn.XLOOKUP(C63,mfscreener.portfolio_holdings_v!$C:$C,mfscreener.portfolio_holdings_v!$D:$D) -> Hybrid | F63: 1304.89 | G63: 0.48 | I63: Mr. Sorbh Gupta (Equity Portion) ,Mr. Anup Kulkarni (Equity Portion), Mr. Siddharth Chaudhary (Debt Portion) ,Mr. Vinay Bafna (Commodity investments portion) | J63: 16, 16, 18, 10
A64: 46022 | B64: Bajaj Finserv Mutual Fund | C64: BAJAJ_BALANCED_ADVANTAGE | D64: =_xlfn.XLOOKUP(C64,mfscreener.portfolio_holdings_v!$C:$C,mfscreener.portfolio_holdings_v!$E:$E) -> Balanced Advantage | E64: =_xlfn.XLOOKUP(C64,mfscreener.portfolio_holdings_v!$C:$C,mfscreener.portfolio_holdings_v!$D:$D) -> Hybrid | F64: 1335.25 | G64: 0.56 | H64: 0.95 | I64: Mr. Nimesh Chandan, Mr. Sorbh Gupta ,Mr. Siddharth Chaudhary | J64: 25,16,18
A65: 46022 | B65: Bajaj Finserv Mutual Fund | C65: BAJAJ_EQUITY_SAVINGS | D65: =_xlfn.XLOOKUP(C65,mfscreener.portfolio_holdings_v!$C:$C,mfscreener.portfolio_holdings_v!$E:$E) -> Equity Savings | E65: =_xlfn.XLOOKUP(C65,mfscreener.portfolio_holdings_v!$C:$C,mfscreener.portfolio_holdings_v!$D:$D) -> Hybrid | F65: 28.76 | G65: 0.3 | I65: Mr. Sorbh Gupta, Mr. Ilesh Savla ,Mr. Siddharth Chaudhary | J65: 16,25,18
A66: 46022 | B66: Bajaj Finserv Mutual Fund | C66: BAJAJ_ARBITRAGE | D66: =_xlfn.XLOOKUP(C66,mfscreener.portfolio_holdings_v!$C:$C,mfscreener.portfolio_holdings_v!$E:$E) -> Arbitrage | E66: =_xlfn.XLOOKUP(C66,mfscreener.portfolio_holdings_v!$C:$C,mfscreener.portfolio_holdings_v!$D:$D) -> Hybrid | F66: 1251.02 | G66: 0.31 | I66: Mr. Ilesh Savla, Mr. Siddharth Chaudhary | J66: 23,18
A67: 46022 | B67: Bajaj Finserv Mutual Fund | C67: BAJAJ_MULTI_CAP | D67: =_xlfn.XLOOKUP(C67,mfscreener.portfolio_holdings_v!$C:$C,mfscreener.portfolio_holdings_v!$E:$E) -> multi cap | E67: =_xlfn.XLOOKUP(C67,mfscreener.portfolio_holdings_v!$C:$C,mfscreener.portfolio_holdings_v!$D:$D) -> equity | F67: 1049.86 | G67: 0.67 | I67: Mr. Nimesh Chandan, Mr. Sorbh Gupta ,Mr. Siddharth Chaudhary | J67: 25,16,18
A68: 46022 | B68: Bank of India Mutual Fund | C68: BOI_FLEXI_CAP | D68: =_xlfn.XLOOKUP(C68,mfscreener.portfolio_holdings_v!$C:$C,mfscreener.portfolio_holdings_v!$E:$E) -> Flexi Cap | E68: =_xlfn.XLOOKUP(C68,mfscreener.portfolio_holdings_v!$C:$C,mfscreener.portfolio_holdings_v!$D:$D) -> Equity | F68: 2227.84 | G68: 0.5 | H68: 0.55 | I68: Mr. Alok Singh | J68: 20
A69: 46022 | B69: Bank of India Mutual Fund | C69: BOI_SMALL_CAP | D69: =_xlfn.XLOOKUP(C69,mfscreener.portfolio_holdings_v!$C:$C,mfscreener.portfolio_holdings_v!$E:$E) -> Small Cap | E69: =_xlfn.XLOOKUP(C69,mfscreener.portfolio_holdings_v!$C:$C,mfscreener.portfolio_holdings_v!$D:$D) -> Equity | F69: 1929.5 | G69: 0.53 | H69: 0.56 | I69: Mr. Alok Singh,Mr Nav Bhardwaj | J69: 20,17
A70: 46022 | B70: Bank of India Mutual Fund | C70: BOI_MULTI_CAP | D70: =_xlfn.XLOOKUP(C70,mfscreener.portfolio_holdings_v!$C:$C,mfscreener.portfolio_holdings_v!$E:$E) -> Multi Cap | E70: =_xlfn.XLOOKUP(C70,mfscreener.portfolio_holdings_v!$C:$C,mfscreener.portfolio_holdings_v!$D:$D) -> Equity | F70: 994.43 | G70: 0.79 | H70: 0.55 | I70: Mr. Nitin Gosar | J70: 16
A71: 46022 | B71: Bank of India Mutual Fund | C71: BOI_MID_CAP | D71: =_xlfn.XLOOKUP(C71,mfscreener.portfolio_holdings_v!$C:$C,mfscreener.portfolio_holdings_v!$E:$E) -> Mid Cap | E71: =_xlfn.XLOOKUP(C71,mfscreener.portfolio_holdings_v!$C:$C,mfscreener.portfolio_holdings_v!$D:$D) -> Equity | F71: 675.86 | G71: 1.12 | H71: 0.13 | I71: Mr. Alok Singh | J71: 20
A72: 46022 | B72: Bank of India Mutual Fund | C72: BOI_LARGE_CAP | D72: =_xlfn.XLOOKUP(C72,mfscreener.portfolio_holdings_v!$C:$C,mfscreener.portfolio_holdings_v!$E:$E) -> Large Cap | E72: =_xlfn.XLOOKUP(C72,mfscreener.portfolio_holdings_v!$C:$C,mfscreener.portfolio_holdings_v!$D:$D) -> Equity | F72: 207.39 | G72: 0.68 | H72: 0.7 | I72: Mr. Alok Singh, Mr Nilesh Jethani | J72: 20,9
A73: 46022 | B73: Bank of India Mutual Fund | C73: BOI_LARGE_MID_CAP | D73: =_xlfn.XLOOKUP(C73,mfscreener.portfolio_holdings_v!$C:$C,mfscreener.portfolio_holdings_v!$E:$E) -> Large & Mid Cap | E73: =_xlfn.XLOOKUP(C73,mfscreener.portfolio_holdings_v!$C:$C,mfscreener.portfolio_holdings_v!$D:$D) -> Equity | F73: 449.58 | G73: 0.82 | H73: 0.53 | I73: Mr. Nitin Gosar | J73: 16
A74: 46022 | B74: Bank of India Mutual Fund | C74: BOI_ELSS | D74: =_xlfn.XLOOKUP(C74,mfscreener.portfolio_holdings_v!$C:$C,mfscreener.portfolio_holdings_v!$E:$E) -> ELSS | E74: =_xlfn.XLOOKUP(C74,mfscreener.portfolio_holdings_v!$C:$C,mfscreener.portfolio_holdings_v!$D:$D) -> Equity | F74: 1388.21 | G74: 0.77 | H74: 0.49 | I74: Mr. Alok Singh | J74: 20
A75: 46022 | B75: Bank of India Mutual Fund | C75: BOI_MANUFACTURING_INFRA | D75: Infrastructure | E75: =_xlfn.XLOOKUP(C75,mfscreener.portfolio_holdings_v!$C:$C,mfscreener.portfolio_holdings_v!$D:$D) -> Equity | F75: 660.6 | G75: 0.62 | H75: 0.5 | I75: Mr. Nitin Gosar | J75: 16
A76: 46022 | B76: Bank of India Mutual Fund | C76: BOI_BUSINESS_CYCLE | D76: =_xlfn.XLOOKUP(C76,mfscreener.portfolio_holdings_v!$C:$C,mfscreener.portfolio_holdings_v!$E:$E) -> Business Cycle | E76: =_xlfn.XLOOKUP(C76,mfscreener.portfolio_holdings_v!$C:$C,mfscreener.portfolio_holdings_v!$D:$D) -> Equity | F76: 512.81 | G76: 1.01 | H76: 0.66 | I76: Mr. Alok Singh | J76: 20
A77: 46022 | B77: Bank of India Mutual Fund | C77: BOI_CONSUMPTION | D77: =_xlfn.XLOOKUP(C77,mfscreener.portfolio_holdings_v!$C:$C,mfscreener.portfolio_holdings_v!$E:$E) -> Consumption | E77: =_xlfn.XLOOKUP(C77,mfscreener.portfolio_holdings_v!$C:$C,mfscreener.portfolio_holdings_v!$D:$D) -> Equity | F77: 416.16 | G77: 1.08 | H77: 0.54 | I77: Mr. Nitin Gosar | J77: 16
A78: 46022 | B78: Bank of India Mutual Fund | C78: BOI_BALANCED_ADVANTAGE | D78: =_xlfn.XLOOKUP(C78,mfscreener.portfolio_holdings_v!$C:$C,mfscreener.portfolio_holdings_v!$E:$E) -> Balanced Advantage | E78: =_xlfn.XLOOKUP(C78,mfscreener.portfolio_holdings_v!$C:$C,mfscreener.portfolio_holdings_v!$D:$D) -> Hybrid | F78: 146.37 | G78: 0.96 | I78: Mr. Alok Singh | J78: 20
A79: 46022 | B79: Bank of India Mutual Fund | C79: BOI_MULTI_ASSET | D79: =_xlfn.XLOOKUP(C79,mfscreener.portfolio_holdings_v!$C:$C,mfscreener.portfolio_holdings_v!$E:$E) -> Multi Asset Allocation | E79: =_xlfn.XLOOKUP(C79,mfscreener.portfolio_holdings_v!$C:$C,mfscreener.portfolio_holdings_v!$D:$D) -> Hybrid | F79: 341.97 | G79: 0.86 | H79: 0.87 | I79: Mr. Mithraem Bharucha,Mr. Nilesh Jethani | J79: 15,9
A80: 46022 | B80: Bank of India Mutual Fund | C80: BOI_CONSERVATIVE_HYBRID | D80: =_xlfn.XLOOKUP(C80,mfscreener.portfolio_holdings_v!$C:$C,mfscreener.portfolio_holdings_v!$E:$E) -> Conservative Hybrid | E80: =_xlfn.XLOOKUP(C80,mfscreener.portfolio_holdings_v!$C:$C,mfscreener.portfolio_holdings_v!$D:$D) -> Hybrid | F80: 65.29 | G80: 1.24 | I80: Mr. Alok Singh | J80: 20
A81: 46022 | B81: Bank of India Mutual Fund | C81: BOI_ARBITRAGE | D81: =_xlfn.XLOOKUP(C81,mfscreener.portfolio_holdings_v!$C:$C,mfscreener.portfolio_holdings_v!$E:$E) -> Arbitrage | E81: =_xlfn.XLOOKUP(C81,mfscreener.portfolio_holdings_v!$C:$C,mfscreener.portfolio_holdings_v!$D:$D) -> Hybrid | F81: 42.38 | G81: 0.37 | I81: Nilesh Jethani | J81: 9
A82: 46022 | B82: Bank of India Mutual Fund | C82: BOI_MID_SMALL_CAP | D82: =_xlfn.XLOOKUP(C82,mfscreener.portfolio_holdings_v!$C:$C,mfscreener.portfolio_holdings_v!$E:$E) -> #N/A | E82: =_xlfn.XLOOKUP(C82,mfscreener.portfolio_holdings_v!$C:$C,mfscreener.portfolio_holdings_v!$D:$D) -> #N/A | F82: 1315.25 | G82: 0.68 | H82: 0.82 | I82: Mr. Alok Singh | J82: 20
A83: 46022 | B83: Baroda BNP Paribas Mutual Fund | C83: BARODA_LARGE_CAP | D83: =_xlfn.XLOOKUP(C83,mfscreener.portfolio_holdings_v!$C:$C,mfscreener.portfolio_holdings_v!$E:$E) -> Large Cap | E83: =_xlfn.XLOOKUP(C83,mfscreener.portfolio_holdings_v!$C:$C,mfscreener.portfolio_holdings_v!$D:$D) -> Equity | F83: 2729.68 | G83: 0.82 | H83: 0.71 | I83: Mr. Jitendra Sriram ,Mr. Kushant Arora | J83: 27,11
A84: 46022 | B84: Baroda BNP Paribas Mutual Fund | C84: BARODA_MID_CAP | D84: =_xlfn.XLOOKUP(C84,mfscreener.portfolio_holdings_v!$C:$C,mfscreener.portfolio_holdings_v!$E:$E) -> Mid Cap | E84: =_xlfn.XLOOKUP(C84,mfscreener.portfolio_holdings_v!$C:$C,mfscreener.portfolio_holdings_v!$D:$D) -> Equity | F84: 2298.06 | G84: 0.55 | H84: 0.8 | I84: Mr. Pratish Krishnan, Mr. Himanshu Singh | J84: 23,10
A85: 46022 | B85: Baroda BNP Paribas Mutual Fund | C85: BARODA_SMALL_CAP | D85: =_xlfn.XLOOKUP(C85,mfscreener.portfolio_holdings_v!$C:$C,mfscreener.portfolio_holdings_v!$E:$E) -> Small Cap | E85: =_xlfn.XLOOKUP(C85,mfscreener.portfolio_holdings_v!$C:$C,mfscreener.portfolio_holdings_v!$D:$D) -> Equity | F85: 1213.7 | G85: 0.95 | H85: 0.94 | I85: Mr. Sanjay Chawla,Mr. Himanshu Singh | J85: 33,10
A86: 46022 | B86: Baroda BNP Paribas Mutual Fund | C86: BARODA_LARGE_MID_CAP | D86: =_xlfn.XLOOKUP(C86,mfscreener.portfolio_holdings_v!$C:$C,mfscreener.portfolio_holdings_v!$E:$E) -> Large & Mid Cap | E86: =_xlfn.XLOOKUP(C86,mfscreener.portfolio_holdings_v!$C:$C,mfscreener.portfolio_holdings_v!$D:$D) -> Equity | F86: 1732.31 | G86: 0.84 | H86: 0.84 | I86: Mr. Sanjay Chawla ,Mr. Kirtan Mehta | J86: 33,26
A87: 46022 | B87: Baroda BNP Paribas Mutual Fund | C87: BARODA_FLEXI_CAP | D87: =_xlfn.XLOOKUP(C87,mfscreener.portfolio_holdings_v!$C:$C,mfscreener.portfolio_holdings_v!$E:$E) -> Flexi Cap | E87: =_xlfn.XLOOKUP(C87,mfscreener.portfolio_holdings_v!$C:$C,mfscreener.portfolio_holdings_v!$D:$D) -> Equity | F87: 1262.44 | G87: 1.01 | H87: 0.84 | I87: Mr. Sanjay Chawla,Mr. Kirtan Mehta | J87: 33,26
A88: 46022 | B88: Baroda BNP Paribas Mutual Fund | C88: BARODA_MULTI_CAP | D88: =_xlfn.XLOOKUP(C88,mfscreener.portfolio_holdings_v!$C:$C,mfscreener.portfolio_holdings_v!$E:$E) -> Multi Cap | E88: =_xlfn.XLOOKUP(C88,mfscreener.portfolio_holdings_v!$C:$C,mfscreener.portfolio_holdings_v!$D:$D) -> Equity | F88: 3119.81 | G88: 0.9 | H88: 1.17 | I88: Mr. Sanjay Chawla,Mr. Kirtan Mehta | J88: 33,26
A89: 46022 | B89: Baroda BNP Paribas Mutual Fund | C89: BARODA_VALUE | D89: =_xlfn.XLOOKUP(C89,mfscreener.portfolio_holdings_v!$C:$C,mfscreener.portfolio_holdings_v!$E:$E) -> Value | E89: =_xlfn.XLOOKUP(C89,mfscreener.portfolio_holdings_v!$C:$C,mfscreener.portfolio_holdings_v!$D:$D) -> Equity | F89: 1172 | G89: 1.16 | H89: 0.7 | I89: Mr. Jitendra Sriram,Mr. Himanshu Singh | J89: 27,10
A90: 46022 | B90: Baroda BNP Paribas Mutual Fund | C90: BARODA_FOCUSED | D90: =_xlfn.XLOOKUP(C90,mfscreener.portfolio_holdings_v!$C:$C,mfscreener.portfolio_holdings_v!$E:$E) -> Focused | E90: =_xlfn.XLOOKUP(C90,mfscreener.portfolio_holdings_v!$C:$C,mfscreener.portfolio_holdings_v!$D:$D) -> Equity | F90: 708.59 | G90: 0.47 | H90: 1.33 | I90: Mr. Sanjay Chawla,Mr. Kirtan Mehta | J90: 33,26
A91: 46022 | B91: Baroda BNP Paribas Mutual Fund | C91: BARODA_DIVIDEND_YIELD | D91: =_xlfn.XLOOKUP(C91,mfscreener.portfolio_holdings_v!$C:$C,mfscreener.portfolio_holdings_v!$E:$E) -> Dividend Yield | E91: =_xlfn.XLOOKUP(C91,mfscreener.portfolio_holdings_v!$C:$C,mfscreener.portfolio_holdings_v!$D:$D) -> Equity | F91: 795.4 | G91: 1.13 | H91: 0.69 | I91: Mr. Jitendra Sriram,Mr. Himanshu Singh | J91: 27,10
A92: 46022 | B92: Baroda BNP Paribas Mutual Fund | C92: BARODA_ELSS | D92: =_xlfn.XLOOKUP(C92,mfscreener.portfolio_holdings_v!$C:$C,mfscreener.portfolio_holdings_v!$E:$E) -> ELSS | E92: =_xlfn.XLOOKUP(C92,mfscreener.portfolio_holdings_v!$C:$C,mfscreener.portfolio_holdings_v!$D:$D) -> Equity | F92: 942.12 | G92: 1 | H92: 0.45 | I92: Mr. Sanjay Chawla, Mr. Pratish Krishnan | J92: 33,23
A93: 46022 | B93: Baroda BNP Paribas Mutual Fund | C93: BARODA_BANKING_FINANCIAL | D93: =_xlfn.XLOOKUP(C93,mfscreener.portfolio_holdings_v!$C:$C,mfscreener.portfolio_holdings_v!$E:$E) -> Banking & Financial Services | E93: =_xlfn.XLOOKUP(C93,mfscreener.portfolio_holdings_v!$C:$C,mfscreener.portfolio_holdings_v!$D:$D) -> Equity | F93: 368.43 | G93: 0.76 | H93: 0.71 | I93: Mr. Sanjay Chawla,Mr. Yash Mehta | J93: 33,1.5
A94: 46022 | B94: Baroda BNP Paribas Mutual Fund | C94: BARODA_MANUFACTURING | D94: =_xlfn.XLOOKUP(C94,mfscreener.portfolio_holdings_v!$C:$C,mfscreener.portfolio_holdings_v!$E:$E) -> Manufacturing | E94: =_xlfn.XLOOKUP(C94,mfscreener.portfolio_holdings_v!$C:$C,mfscreener.portfolio_holdings_v!$D:$D) -> Equity | F94: 988.9 | G94: 1.14 | H94: 0.52 | I94: Mr. Jitendra Sriram,Mr. Kushant Arora | J94: 27,11
A95: 46022 | B95: Baroda BNP Paribas Mutual Fund | C95: BARODA_INNOVATION | D95: Innovation | E95: =_xlfn.XLOOKUP(C95,mfscreener.portfolio_holdings_v!$C:$C,mfscreener.portfolio_holdings_v!$D:$D) -> Equity | F95: 935.69 | G95: 1.01 | H95: 0.72 | I95: Mr. Pratish Krishnan,Mr. Ankeet Pandya | J95: 23,11
A96: 46022 | B96: Baroda BNP Paribas Mutual Fund | C96: BARODA_INDIA_CONSUMPTION | D96: Consumption | E96: =_xlfn.XLOOKUP(C96,mfscreener.portfolio_holdings_v!$C:$C,mfscreener.portfolio_holdings_v!$D:$D) -> Equity | F96: 1538.71 | G96: 0.64 | H96: 0.71 | I96: Mr. Pratish Krishnan,Mr. Himanshu Singh | J96: 23,10
A97: 46022 | B97: Baroda BNP Paribas Mutual Fund | C97: BARODA_ENERGY_OPPORTUNITIES | D97: Energy | E97: =_xlfn.XLOOKUP(C97,mfscreener.portfolio_holdings_v!$C:$C,mfscreener.portfolio_holdings_v!$D:$D) -> Equity | F97: 711.74 | G97: 1.01 | H97: 0.65 | I97: Mr. Sanjay Chawla,Mr. Kirtan Mehta | J97: 33,26
A98: 46022 | B98: Baroda BNP Paribas Mutual Fund | C98: BARODA_HEALTH_WELLNESS | D98: Healthcare | E98: =_xlfn.XLOOKUP(C98,mfscreener.portfolio_holdings_v!$C:$C,mfscreener.portfolio_holdings_v!$D:$D) -> Equity | F98: 592.7 | G98: 0.59 | H98: 0.33 | I98: Mr. Sanjay Chawla | J98: 33
A99: 46022 | B99: Baroda BNP Paribas Mutual Fund | C99: BARODA_BUSINESS_CONGLOMERATES | D99: Business Conglomerates | E99: =_xlfn.XLOOKUP(C99,mfscreener.portfolio_holdings_v!$C:$C,mfscreener.portfolio_holdings_v!$D:$D) -> Equity | F99: 768.92 | G99: 0.59 | H99: 0.04 | I99: Mr. Jitendra Sriram,Mr. Kushant Arora | J99: 27,11
A100: 46022 | B100: Baroda BNP Paribas Mutual Fund | C100: BARODA_BUSINESS_CYCLE | D100: Business Cycle | E100: =_xlfn.XLOOKUP(C100,mfscreener.portfolio_holdings_v!$C:$C,mfscreener.portfolio_holdings_v!$D:$D) -> Equity | F100: 585.17 | G100: 0.92 | H100: 0.69 | I100: Mr. Jitendra Sriram,Mr. Kushant Arora | J100: 27,11
...

Sheet mfscreener.portfolio_holdings_v
A1: as_of | B1: amc | C1: fund_key | D1: asset_class | E1: category
A2: 46022 | B2: Aditya Birla Sun Life Mutual Fund | C2: ABSL_LARGE_CAP | D2: Equity | E2: Large Cap
A3: 46022 | B3: Aditya Birla Sun Life Mutual Fund | C3: ABSL_LARGE_MID_CAP | D3: Equity | E3: Large & Mid Cap
A4: 46022 | B4: Aditya Birla Sun Life Mutual Fund | C4: ABSL_MID_CAP | D4: Equity | E4: Mid Cap
A5: 46022 | B5: Aditya Birla Sun Life Mutual Fund | C5: ABSL_SMALL_CAP | D5: Equity | E5: Small Cap
A6: 46022 | B6: Aditya Birla Sun Life Mutual Fund | C6: ABSL_FLEXI_CAP | D6: Equity | E6: Flexi Cap
A7: 46022 | B7: Aditya Birla Sun Life Mutual Fund | C7: ABSL_MULTI_CAP | D7: Equity | E7: Multi Cap
A8: 46022 | B8: Aditya Birla Sun Life Mutual Fund | C8: ABSL_VALUE | D8: Equity | E8: Value
A9: 46022 | B9: Aditya Birla Sun Life Mutual Fund | C9: ABSL_ELSS | D9: Equity | E9: ELSS
A10: 46022 | B10: Aditya Birla Sun Life Mutual Fund | C10: ABSL_FOCUSED | D10: Equity | E10: Focused
A11: 46022 | B11: Aditya Birla Sun Life Mutual Fund | C11: ABSL_BANKING_FINANCIAL | D11: Equity | E11: Banking & Financial Services
A12: 46022 | B12: Aditya Birla Sun Life Mutual Fund | C12: ABSL_MANUFACTURING | D12: Equity | E12: Manufacturing Equity
A13: 46022 | B13: Aditya Birla Sun Life Mutual Fund | C13: ABSL_PSU_EQUITY | D13: Equity | E13: PSU Equity
... A672: 46022 | B672: UTI Mutual Fund | C672: UTI_MULTI_ASSET | D672: Hybrid | E672: Multi Asset
